awaken2/__init__.py
awaken2/awaken_console.py
awaken2/baseic/__init__.py
awaken2/baseic/broadcast/__init__.py
awaken2/baseic/broadcast/awaken_log.py
awaken2/baseic/common/__init__.py
awaken2/baseic/common/configure.py
awaken2/baseic/common/convert.py
awaken2/baseic/common/encryption.py
awaken2/baseic/common/template_rendering.py
awaken2/baseic/const/__init__.py
awaken2/baseic/const/const_api.py
awaken2/baseic/const/const_common.py
awaken2/baseic/const/const_interpreter.py
awaken2/baseic/const/const_name.py
awaken2/baseic/const/const_path.py
awaken2/baseic/const/const_state.py
awaken2/baseic/const/const_type.py
awaken2/baseic/decorator/__init__.py
awaken2/baseic/decorator/baseic.py
awaken2/baseic/decorator/unit_testing.py
awaken2/baseic/decorator/web_api.py
awaken2/baseic/environment/__init__.py
awaken2/baseic/environment/common.py
awaken2/baseic/environment/project_file_handle.py
awaken2/baseic/environment/web/__init__.py
awaken2/baseic/environment/web/browser_driver_handle.py
awaken2/baseic/error/__init__.py
awaken2/baseic/error/baseic.py
awaken2/baseic/error/broadcast.py
awaken2/baseic/error/database.py
awaken2/baseic/error/engine.py
awaken2/baseic/error/file.py
awaken2/baseic/error/interpreter.py
awaken2/baseic/error/project.py
awaken2/baseic/error/server.py
awaken2/baseic/error/type_error.py
awaken2/baseic/keyword/__init__.py
awaken2/baseic/keyword/keyword_api.py
awaken2/baseic/keyword/keyword_common.py
awaken2/baseic/keyword/keyword_database.py
awaken2/baseic/keyword/keyword_script.py
awaken2/baseic/keyword/keyword_sqlite.py
awaken2/baseic/structural/__init__.py
awaken2/baseic/structural/interpreter.py
awaken2/core/__init__.py
awaken2/core/interpreter/__init__.py
awaken2/core/interpreter/base_code_converter.py
awaken2/core/interpreter/grammar_parser.py
awaken2/core/interpreter/task_preprocessor.py
awaken2/core/perform/__init__.py
awaken2/core/perform/perform_pool.py
awaken2/core/perform/perform_server.py
awaken2/core/perform/pool_runtime.py
awaken2-0.2.4.dist-info/LICENSE
awaken2-0.2.4.dist-info/METADATA
awaken2-0.2.4.dist-info/WHEEL
awaken2-0.2.4.dist-info/entry_points.txt
awaken2-0.2.4.dist-info/top_level.txt
awaken2-0.2.4.dist-info/RECORD
