Metadata-Version: 2.1
Name: awaken2
Version: 0.2.4
Summary: Awaken 是一个功能自动化测试框架, 将支持 WEB、API、APP 等平台。
Home-page: https://gitee.com/catcat7/awaken2
Author: chenjiancheng
Author-email: quinn.7@foxmail.com
License: UNKNOWN
Keywords: awaken2,python,testing,automation,testautomation
Platform: UNKNOWN
Classifier: Programming Language :: Python :: 3.10
License-File: LICENSE
Requires-Dist: playwright
Requires-Dist: flask
Requires-Dist: websockets-routes
